{
  "101": [
    "BHS",
    "BRB",
    "BLZ",
    "CYM",
    "CRI",
    "CUW",
    "SLV",
    "GRD",
    "JAM",
    "MEX",
    "KNA",
    "LCA",
    "SXM",
    "TTO"
  ],
  "102": [
    "AUT",
    "BEL",
    "CYP",
    "CZE",
    "DNK",
    "FIN",
    "FRA",
    "DEU",
    "GRC",
    "HUN",
    "ISL",
    "IRL",
    "ITA",
    "LIE",
    "LUX",
    "MLT",
    "MCO",
    "NLD",
    "NOR",
    "PRT",
    "SMR",
    "ESP",
    "SWE",
    "CHE",
    "GBR"
  ],
  "103": [
    "ALB",
    "BLR",
    "HRV",
    "EST",
    "LVA",
    "LTU",
    "POL",
    "ROU",
    "RUS",
    "SRB",
    "SVK"
  ],
  "104": ["HKG", "JPN", "KOR", "MAC", "MYS", "SGP", "TWN", "THA"],
  "105": ["AUS", "NZL", "NFK"],
  "106": ["IND", "IDN", "PHL", "VNM"],
  "107": ["ARG", "BRA", "CHL", "COL", "ECU", "GUY"],
  "108": ["ISR", "LBN", "SAU", "SYR", "ARE"],
  "109": ["CHN"],
  "110": ["ETH", "KEN", "MUS", "MAR"]
}
